custom_decision_trees/__init__.py
custom_decision_trees/utils.py
custom_decision_trees/metrics/__init__.py
custom_decision_trees/metrics/entropy.py
custom_decision_trees/metrics/gini.py
custom_decision_trees/metrics/metric_base.py
custom_decision_trees/metrics/mse.py
custom_decision_trees/models/__init__.py
custom_decision_trees/models/decision_tree.py
custom_decision_trees/models/decision_tree_classifier.py
custom_decision_trees/models/decision_tree_regressor.py
custom_decision_trees/models/random_forest.py
custom_decision_trees/models/random_forest_classifier.py
custom_decision_trees/models/random_forest_regressor.py
custom_decision_trees/models/schemas.py
custom_decision_trees-3.0.1.dist-info/licenses/LICENSE
custom_decision_trees-3.0.1.dist-info/METADATA
custom_decision_trees-3.0.1.dist-info/WHEEL
custom_decision_trees-3.0.1.dist-info/top_level.txt
custom_decision_trees-3.0.1.dist-info/RECORD
