Metadata-Version: 2.4
Name: custom-decision-trees
Version: 3.0.1
Summary: A package for building customizable decision trees and random forests.
Home-page: https://github.com/AntoinePinto/custom-decision-trees
Author: Antoine Pinto
Author-email: antoine.pinto1@outlook.fr
License: MIT
Project-URL: Source Code, https://github.com/AntoinePinto/custom-decision-trees
Keywords: machine learning,decision trees,random forest,customization,classification,custom splitting criteria
Requires-Python: >=3.10
License-File: LICENSE
Requires-Dist: joblib>=1.4.0
Requires-Dist: matplotlib>=3.9.0
Requires-Dist: numpy>=1.26.0
Dynamic: author
Dynamic: author-email
Dynamic: description
Dynamic: description-content-type
Dynamic: home-page
Dynamic: keywords
Dynamic: license
Dynamic: license-file
Dynamic: project-url
Dynamic: requires-dist
Dynamic: requires-python
Dynamic: summary
